<?xml version="1.0" encoding="UTF-8"?>
<dataroot xmlns:od="urn:schemas-microsoft-com:officedata" xmlns:xsi="http://www.w3.org/2001/XMLSchema-instance"  xsi:noNamespaceSchemaLocation="battle_city_subculture_jct.xsd" generated="2009-08-17T14:01:02">
<battle_city_subculture_jct>
<subculture>sc_european_america</subculture>
<city>American</city>
<s_ColLineage>NAnHjgIAAAA0CceOAgAAAA==
</s_ColLineage>
<s_Generation>0</s_Generation>
<s_GUID>{221BD6BE-0498-4C64-833B-1880D58D11BE}</s_GUID>
<s_Lineage>NAnHjgIAAAAAAAAAAAAAAA==
</s_Lineage>
</battle_city_subculture_jct>
<battle_city_subculture_jct>
<subculture>sc_european_east</subculture>
<city>European</city>
<s_ColLineage>NAnHjgIAAAA0CceOAgAAAA==
</s_ColLineage>
<s_Generation>0</s_Generation>
<s_GUID>{3EB3324F-8F31-40A2-8E39-5A7ECA2C9D1E}</s_GUID>
<s_Lineage>NAnHjgIAAAAAAAAAAAAAAA==
</s_Lineage>
</battle_city_subculture_jct>
<battle_city_subculture_jct>
<subculture>sc_european_north</subculture>
<city>European</city>
<s_ColLineage>NAnHjgIAAAA0CceOAgAAAA==
</s_ColLineage>
<s_Generation>0</s_Generation>
<s_GUID>{2B22B0B3-38B5-4AB6-BAA7-476EEA311FC7}</s_GUID>
<s_Lineage>NAnHjgIAAAAAAAAAAAAAAA==
</s_Lineage>
</battle_city_subculture_jct>
<battle_city_subculture_jct>
<subculture>sc_european_south</subculture>
<city>European</city>
<s_ColLineage>NAnHjgIAAAA0CceOAgAAAA==
</s_ColLineage>
<s_Generation>0</s_Generation>
<s_GUID>{06DC2EB6-5740-4DDB-9079-7F8EA76C9C5A}</s_GUID>
<s_Lineage>NAnHjgIAAAAAAAAAAAAAAA==
</s_Lineage>
</battle_city_subculture_jct>
<battle_city_subculture_jct>
<subculture>sc_european_west</subculture>
<city>European</city>
<s_ColLineage>NAnHjgIAAAA0CceOAgAAAA==
</s_ColLineage>
<s_Generation>0</s_Generation>
<s_GUID>{73CCF3D0-ECF2-4198-A76B-C72600E81903}</s_GUID>
<s_Lineage>NAnHjgIAAAAAAAAAAAAAAA==
</s_Lineage>
</battle_city_subculture_jct>
<battle_city_subculture_jct>
<subculture>sc_indian_hindu</subculture>
<city>Eastern</city>
<s_ColLineage>NAnHjgMAAAA0CceOAgAAAA==
</s_ColLineage>
<s_Generation>0</s_Generation>
<s_GUID>{4CF1C7B8-76EE-458F-96F2-5DDA89867DA8}</s_GUID>
<s_Lineage>NAnHjgMAAAAAAAAAAAAAAA==
</s_Lineage>
</battle_city_subculture_jct>
<battle_city_subculture_jct>
<subculture>sc_indian_islamic</subculture>
<city>Eastern</city>
<s_ColLineage>NAnHjgMAAAA0CceOAgAAAA==
</s_ColLineage>
<s_Generation>0</s_Generation>
<s_GUID>{4EEBCCEF-3E7D-4B14-8BA5-F5BBC7D6124E}</s_GUID>
<s_Lineage>NAnHjgMAAAAAAAAAAAAAAA==
</s_Lineage>
</battle_city_subculture_jct>
<battle_city_subculture_jct>
<subculture>sc_indian_sikh</subculture>
<city>Eastern</city>
<s_ColLineage>NAnHjgMAAAA0CceOAgAAAA==
</s_ColLineage>
<s_Generation>0</s_Generation>
<s_GUID>{D1AE7A31-4793-4627-8EF0-AE5AB1FF476E}</s_GUID>
<s_Lineage>NAnHjgMAAAAAAAAAAAAAAA==
</s_Lineage>
</battle_city_subculture_jct>
<battle_city_subculture_jct>
<subculture>sc_mideast_islamic</subculture>
<city>Eastern</city>
<s_ColLineage>NAnHjgMAAAA0CceOAgAAAA==
</s_ColLineage>
<s_Generation>0</s_Generation>
<s_GUID>{C5FB9636-AD4E-4E36-B951-2E9F07AAEDFD}</s_GUID>
<s_Lineage>NAnHjgMAAAAAAAAAAAAAAA==
</s_Lineage>
</battle_city_subculture_jct>
<battle_city_subculture_jct>
<subculture>sc_tribal_american</subculture>
<city>Native</city>
<s_ColLineage>NAnHjgIAAAA0CceOAgAAAA==
</s_ColLineage>
<s_Generation>0</s_Generation>
<s_GUID>{7271D508-B591-48D1-98C0-0E637B85AE00}</s_GUID>
<s_Lineage>NAnHjgIAAAAAAAAAAAAAAA==
</s_Lineage>
</battle_city_subculture_jct>
<battle_city_subculture_jct>
<subculture>sc_egy_middle_east</subculture>
<city>Eastern</city>
<s_ColLineage>W4e7tQIAAABbh7u1AgAAAA==
</s_ColLineage>
<s_Generation>0</s_Generation>
<s_GUID>{3F3C31E7-28B9-4A67-ADA8-BD757C66A4AC}</s_GUID>
<s_Lineage>W4e7tQIAAAAAAAAAAAAAAA==
</s_Lineage>
</battle_city_subculture_jct>
<battle_city_subculture_jct>
<subculture>sc_egy_european</subculture>
<city>European</city>
<s_ColLineage>W4e7tQIAAABbh7u1AgAAAA==
</s_ColLineage>
<s_Generation>0</s_Generation>
<s_GUID>{BA956711-E85D-4169-A4FE-52658B5A31AE}</s_GUID>
<s_Lineage>W4e7tQIAAAAAAAAAAAAAAA==
</s_Lineage>
</battle_city_subculture_jct>
</dataroot>
